cinemate-0.2.1.dist-info/RECORD
cinemate-0.2.1.dist-info/WHEEL
cinemate-0.2.1.dist-info/metadata.json
cinemate-0.2.1.dist-info/DESCRIPTION.rst
cinemate-0.2.1.dist-info/METADATA
cinemate-0.2.1.dist-info/top_level.txt
tests/test_utils.py
tests/test_stats.py
tests/test_person.py
tests/test_movie.py
tests/test_cinemate.py
tests/test_account.py
tests/data.py
tests/conftest.py
tests/__init__.py
cinemate/version.py
cinemate/utils.py
cinemate/stats.py
cinemate/person.py
cinemate/movie.py
cinemate/lists.py
cinemate/cinemate.py
cinemate/account.py
cinemate/__init__.py
